sdect/sd.vhdl
library IEEE;
use IEEE.STD_LOGIC_1164.ALL;

entity sd is
port (
 CLK: in std_logic;
 RST: in std_logic;
 X: in std_logic;
 Z: out std_logic
);
end sd;

architecture sdarc of sd is
type state is (Q0, Q1, Q2, Q3, Q4);
signal currentState, nextState: state;

begin

seq_proc: process(CLK,RST) is
begin

if(RST='1') then
    currentState <= Q0;
elsif(rising_edge(CLK)) then
    currentState <= nextState;
end if;

end process seq_proc;


comb_proc: process(currentState,X) is
begin

case(currentState) is

    when Q0 =>
    if(X='1') then
   -- "1"
        nextState <= Q1;
    else
        nextState <= Q0;
    end if;
    
    when Q1 =>
    if(X='0') then
    -- "10"
        nextState <= Q2;
    else
        nextState <= Q1;
    end if;  
    
    when Q2 => 
    if(X='1') then
   -- "101"
        nextState <= Q3;
    else
        nextState <= Q0;
    end if;  
    
    when Q3 =>
    if(X='1') then
    -- "1011"
        nextState <= Q4;
    else
        nextState <= Q0;
    end if; 
 
    when Q4 =>
    if(X='0') then
        nextState <= Q0;
    else
        nextState <= Q1;
    end if;

end case;
end process comb_proc;
out_proc: process(currentState) is
begin 
    case currentState is
    when Q0 =>
    Z <= '0';
    
    when Q1 =>
    Z <= '0'; 
 
    when Q2 => 
    Z <= '0'; 
 
    when Q3 =>
    Z <= '0'; 
 
    when Q4 =>
    Z <= '1';
    
    end case;
end process out_proc;
end sdarc;

sdect/sd_tb.vhdl
LIBRARY ieee;
USE ieee.std_logic_1164.ALL;
 
ENTITY tb IS
END tb;
 
ARCHITECTURE tbarc OF tb IS 
   
    
    

    signal CLK,RST,X : std_logic := '0';
    signal Z : std_logic;

 constant CLK_period : time := 10 ns;
 
BEGIN
   uut: entity work.sd PORT MAP (
          CLK => CLK,
          RST => RST,
          X => X,
          Z => Z
        );

    -- CLK process 
    CLK_process :process
    begin
    
    CLK <= '0';
    wait for CLK_period/2;
    CLK <= '1';
    wait for CLK_period/2;
    
    end process;
 

sim: process
    begin  
    
    X <= '0';
    RST <= '1';
    wait for 30 ns;

    RST <= '0';
    wait for 40 ns;
    
    X <= '1';
    wait for 10 ns;
    X <= '0';
    wait for 10 ns;
    X <= '1'; 
    wait for 10 ns;
    X <= '1'; 
    wait for 10 ns;
    X <= '0'; 
    wait for 10 ns;
    X <= '0'; 
    -- insert stimulus here 
    
    wait;
   end process sim;

end tbarc;

sdect/sd.vcd
$date
  Fri Feb  9 19:30:16 2024
$end
$version
  GHDL v0
$end
$timescale
  1 fs
$end
$scope module standard $end
$upscope $end
$scope module std_logic_1164 $end
$upscope $end
$scope module tb $end
$var reg 1 ! clk $end
$var reg 1 " rst $end
$var reg 1 # x $end
$var reg 1 $ z $end
$scope module uut $end
$var reg 1 % clk $end
$var reg 1 & rst $end
$var reg 1 ' x $end
$var reg 1 ( z $end
$comment currentstate is not handled $end
$comment nextstate is not handled $end
$upscope $end
$upscope $end
$enddefinitions $end
#0
0!
1"
0#
0$
0%
1&
0'
0(
#5000000
1!
1%
#10000000
0!
0%
#15000000
1!
1%
#20000000
0!
0%
#25000000
1!
1%
#30000000
0!
0"
0%
0&
#35000000
1!
1%
#40000000
0!
0%
#45000000
1!
1%
#50000000
0!
0%
#55000000
1!
1%
#60000000
0!
0%
#65000000
1!
1%
#70000000
0!
1#
0%
1'
#75000000
1!
1%
#80000000
0!
0#
0%
0'
#85000000
1!
1%
#90000000
0!
1#
0%
1'
#95000000
1!
1%
#100000000
0!
0%
#105000000
1!
1$
1%
1(
#110000000
0!
0#
0%
0'
#115000000
1!
0$
1%
0(
